mdx_titlecase/__init__.py
mdx_titlecase/mdx_titlecase.py
mdx_titlecase/tests/__init__.py
mdx_titlecase/tests/test_mdx_titlecase.py
mdx_titlecase-1.2.0.dist-info/METADATA
mdx_titlecase-1.2.0.dist-info/RECORD
mdx_titlecase-1.2.0.dist-info/WHEEL
mdx_titlecase-1.2.0.dist-info/top_level.txt
