Metadata-Version: 2.1
Name: mdx-titlecase
Version: 1.2.0
Summary: Proper title-casing for Python's Markdown.
Home-page: https://github.com/kdeldycke/mdx_titlecase
Author: Kevin Deldycke
Author-email: kevin@deldycke.com
License: GPLv2+
Platform: UNKNOWN
Classifier: Development Status :: 5 - Production/Stable
Classifier: Intended Audience :: Developers
Classifier: Intended Audience :: Information Technology
Classifier: License :: OSI Approved :: GNU General Public License v2 or later (GPLv2+)
Classifier: Operating System :: OS Independent
Classifier: Programming Language :: Python
Classifier: Programming Language :: Python :: 2
Classifier: Programming Language :: Python :: 2.7
Classifier: Programming Language :: Python :: 3
Classifier: Programming Language :: Python :: 3.3
Classifier: Programming Language :: Python :: 3.4
Classifier: Programming Language :: Python :: 3.5
Classifier: Programming Language :: Python :: Implementation :: PyPy
Classifier: Topic :: Text Processing :: Filters
Classifier: Topic :: Text Processing :: Markup
Requires-Dist: Markdown (>=2.6)
Requires-Dist: titlecase
